{"organizations": [], "uuid": "05e071b6dacf273927fec0aca5c9525c8756bdb0", "thread": {"social": {"gplus": {"shares": 0}, "pinterest": {"shares": 0}, "vk": {"shares": 0}, "linkedin": {"shares": 0}, "facebook": {"likes": 0, "shares": 0, "comments": 0}, "stumbledupon": {"shares": 0}}, "site_full": "echo.msk.ru", "main_image": "http://echo.msk.ru/i/big_logo.png", "site_section": "http://echo.msk.ru/news/", "section_title": "Эхо Москвы :: Новости ", "url": "http://echo.msk.ru/news/1849560-echo.html", "country": "BZ", "domain_rank": 1609, "title": "В России стали искать способы перехвата и расшифровки переписки в популярных интернет-мессенджерах", "performance_score": 0, "site": "echo.msk.ru", "participants_count": 4, "title_full": "Эхо Москвы :: Новости / В России стали искать способы перехвата и расшифровки переписки в популярных интернет-мессенджерах", "spam_score": 0.009, "site_type": "news", "published": "2016-10-04T15:31:00.000+03:00", "replies_count": 3, "uuid": "05e071b6dacf273927fec0aca5c9525c8756bdb0"}, "author": "echo.msk.ru", "url": "http://echo.msk.ru/news/1849560-echo.html", "ord_in_thread": 0, "title": "В России стали искать способы перехвата и расшифровки переписки в популярных интернет-мессенджерах", "locations": [], "entities": {"persons": [], "locations": [], "organizations": []}, "highlightText": "", "language": "russian", "persons": [], "text": "В их числе WhatsApp, Viber, Telegram, Facebook Messenger и Skype. Как пишет газета «Коммерсантъ» , это необходимо для реализации «закона Яровой», в рамках которого для борьбы с терроризмом власти намерены осуществлять перехват и полную дешифровку трафика россиян. Успех в поиске уязвимостей заказчик работ оценил в 330 тысяч рублей за один мессенджер, что довольно дешево, отмечают эксперты. По словам специалистов, до сих пор организовать массовый доступ к переписке в мессенджерах никому не удавалось.", "external_links": ["http://www.kommersant.ru/"], "published": "2016-10-04T15:31:00.000+03:00", "crawled": "2016-10-04T11:04:33.661+03:00", "highlightTitle": ""}